telugu_words_numbers/__init__.py
telugu_words_numbers/telugu_word_to_number.py
telugu_words_numbers/json_files/telugu_numbers.json
telugu_words_numbers-0.0.8.dist-info/LICENSE
telugu_words_numbers-0.0.8.dist-info/METADATA
telugu_words_numbers-0.0.8.dist-info/WHEEL
telugu_words_numbers-0.0.8.dist-info/top_level.txt
telugu_words_numbers-0.0.8.dist-info/RECORD
