Metadata-Version: 2.1
Name: telugu-words-numbers
Version: 0.0.8
Summary: Telugu words to numbers conversion
Home-page: https://github.com/Sandeep-Panchal/telugu-word-to-number-conversion/tree/main
Author: Sandeep Panchal
Author-email: sandeep.panchal545@gmail.com
License: MIT
Project-URL: Bug Tracker, https://github.com/Sandeep-Panchal/telugu-word-to-number-conversion/issues
Keywords: telugu,words,numbers,conversion,words to number,words to number conversion,telugu words number conversion
Platform: UNKNOWN
Classifier: Development Status :: 1 - Planning
Classifier: Intended Audience :: Developers
Classifier: Programming Language :: Python :: 3
Classifier: License :: OSI Approved :: MIT License
Classifier: Operating System :: OS Independent
License-File: LICENSE
Requires-Dist: text2digits
Requires-Dist: numpy
